md5util/__init__.py
md5util/util.py
md5util-0.0.3.dist-info/METADATA
md5util-0.0.3.dist-info/WHEEL
md5util-0.0.3.dist-info/top_level.txt
md5util-0.0.3.dist-info/zip-safe
md5util-0.0.3.dist-info/RECORD
