Metadata-Version: 1.0
Name: md5util
Version: 0.0.3
Summary: a quick md5 tool
Home-page: UNKNOWN
Author: Peng Shiyu
Author-email: pengshiyuyx@gmail.com
License: MIT
Keywords: md5util
Platform: UNKNOWN
